{"Name":"Romanian","Resources":[{"Name":"Baptism","PDFLink":"Botez.pdf","ODTLink":"Botez.odt"},{"Name":"Prayer","PDFLink":"Rugaciunea.pdf","ODTLink":"Rugaciunea.odt"},{"Name":"Forgiving Step by Step","PDFLink":"Paşi_spre_iertare.pdf","ODTLink":"Paşi_spre_iertare.odt"},{"Name":"Confessing Sins and Repenting","PDFLink":"Mărturisirea_păcatelor_şi_pocăinţa.pdf","ODTLink":"Mărturisirea_păcatelor_şi_pocăinţa.odt"},{"Name":"Time with God","PDFLink":"3_Timp_cu_Dumnezeu.pdf","ODTLink":"3_Timp_cu_Dumnezeu.odt"},{"Name":"Hearing from God","PDFLink":"Auzind_de_la_Dumnezeu.pdf","ODTLink":"Auzind_de_la_Dumnezeu.odt"},{"Name":"Church","PDFLink":"Biserica.pdf","ODTLink":"Biserica"},{"Name":"Healing","PDFLink":"Vindecare.pdf","ODTLink":"Vindecare.odt"},{"Name":"My Story with God","PDFLink":"Povestea_mea_cu_Dumnezeu.pdf","ODTLink":"Povestea_mea_cu_Dumnezeu.odt"},{"Name":"Bible Reading Bookmark","PDFLink":"Cum_Să_CItesti_Biblia.pdf","ODTLink":"Cum_Să_Citești_Biblia.odt"},{"Name":"The Three-Thirds Process","PDFLink":"Procesul-în Trei părți.pdf","ODTLink":""},{"Name":"Training Meeting Outline","PDFLink":"Desfășurarea_ședințelor_de_training.pdf","ODTLink":"Desfășurarea_ședințelor_de_training.odt"},{"Name":"A Daily Prayer","PDFLink":"Rugaciunea_de_fiecare_zi.pdf","ODTLink":"Rugaciunea_de_fiecare_zi.odt"},{"Name":"God's Story (five fingers)","PDFLink":"Povestea_lui_Dumnezeu_(cinci_degete).pdf","ODTLink":"Povestea_lui_Dumnezeu_(cinci_degete).odt"},{"Name":"God's Story (first and last sacrifice)","PDFLink":"Povestea_lui_Dumnezeu_(primul_şi_ultimul_sacrificu).pdf","ODTLink":"Povestea_lui_Dumnezeu_(primul_şi_ultimul_sacrificu).odt"},{"Name":"Overcoming Fear and Anger","PDFLink":"A_depăşi_teama_şi_mânia.pdf","ODTLink":"A_depăşi_teama_şi_mânia.odt"},{"Name":"Getting Rid of Colored Lenses","PDFLink":"Renunțând_la_Ochelarii_cu_Lentile_Colorate.pdf","ODTLink":"Renunțând_la_Ochelarii_cu_Lentile_Colorate.odt"},{"Name":"Family and our Relationship with God","PDFLink":"Familia_și_relația_noastră_cu_Dumnezeu.pdf","ODTLink":"Familia_și_relația_noastră_cu_Dumnezeu.odt"},{"Name":"Overcoming Negative Inheritance","PDFLink":"Depășirea_moștenirii_negative.pdf","ODTLink":"Depășirea_moștenirii_negative.odt"},{"Name":"Forgiving Step by Step: Training Notes","PDFLink":"Iertarea Pas cu Pas_Notițe_Pentru_Antrenament.pdf","ODTLink":"Iertarea Pas cu Pas_Notițe_Pentru_Antrenament.odt"},{"Name":"Leading Others Through Forgiveness","PDFLink":"Conducerea_celorlalți_prin_iertare.pdf","ODTLink":"Conducerea_celorlalți_prin_iertare.odt"},{"Name":"The Role of a Helper in Prayer","PDFLink":"Rolul_unui_ajutor_în_rugăciune.pdf","ODTLink":"Rolul_unui_ajutor_în_rugăciune.odt"},{"Name":"Four Kinds of Disciples","PDFLink":"Patru_tipuri_de_ucenici.pdf","ODTLink":"Patru_tipuri_de_ucenici.odt"}]}